{"executionTime":1,"dereferenced":false,"dossierLegislatif":{"id":"JORFDOLE000030746604","ancienId":null,"origine":"JORF","url":"dossiers_legislatifs/JORF/DOLE/00/00/30/74/66/JORFDOLE000030746604.xml","nature":null,"titre":"LOI n° 2016-832 du 24 juin 2016 visant à lutter contre la discrimination à raison de la précarité sociale","type":"LOI_PUBLIEE","dateCreation":1466812800000,"dateDerniereModification":1467244800000,"legislature":{"id":"14","libelle":"XIVème législature","dateDebut":1340668800000,"dateFin":1498435200000},"echeancier":"","exposeMotif":"","arborescence":{"niveaux":[{"id":"1434643608322","libelle":"Dossiers législatifs","niveaux":[{"id":"1434643608324","libelle":"Sénat","niveaux":[],"liens":[{"id":"1434643930054","libelle":"Dossier législatif du Sénat","lien":"http://www.senat.fr/dossier-legislatif/ppl14-378.html","data":""}]},{"id":"1434643608323","libelle":"Assemblée nationale","niveaux":[],"liens":[{"id":"1434644273319","libelle":"Dossier législatif de l'Assemblée nationale","lien":"http://www.assemblee-nationale.fr/14/dossiers/discrimination_precarite_sociale.asp","data":""}]}],"liens":[]},{"id":"1434643608325","libelle":"Documents préparatoires","niveaux":[],"liens":[{"id":"1434643776884","libelle":"Rapport n° 507 de M. Philippe Kaltenbach","lien":"http://www.senat.fr/rap/l14-507/l14-507.html","data":""},{"id":"1434643809017","libelle":"Texte de la commission déposé le 10 juin 2015","lien":"http://www.senat.fr/leg/ppl14-508.html","data":""},{"id":"1465988023269","libelle":"Rapport n° 3799 de M. Michel Ménard","lien":"http://www.assemblee-nationale.fr/14/rapports/r3799.asp","data":""},{"id":"1465988067779","libelle":"Texte de la commission déposé le 1er juin 2016","lien":"http://www.assemblee-nationale.fr/14/ta-commission/r3799-a0.asp","data":""}]},{"id":"1434643608326","libelle":"Débats parlementaires","niveaux":[{"id":"1434643608328","libelle":"Sénat (1ère lecture)","niveaux":[],"liens":[{"id":"1434644191161","libelle":"Compte rendu intégral de la séance du 18 juin 2015","lien":"http://www.senat.fr/seances/s201506/s20150618/s20150618_mono.html#Niv1_SOM5","data":": discussion générale, discussion de l'article unique, interventions et vote sur l'ensemble."}]},{"id":"1434643608327","libelle":"Assemblée nationale (1ère lecture)","niveaux":[{"id":"1465987465153","libelle":"Compte rendu intégral des séances du 14 juin 2016 ‎","niveaux":[],"liens":[{"id":"1465987786386","libelle":"‎2ème séance du 14 juin 2016‎","lien":"http://www.assemblee-nationale.fr/14/cri/2015-2016/20160214.asp#P812066","data":"‎: présentation, discussion générale, discussion de l'article unique‎, vote sur l’article unique"}]}],"liens":[]}],"liens":[]}],"liens":[{"id":"1434643721667","libelle":"Proposition de loi ","lien":"http://www.senat.fr/leg/ppl14-378.html","data":""},{"id":"1434643876431","libelle":"Texte adopté en 1ère lecture par le Sénat le 18 juin 2015","lien":"http://www.senat.fr/petite-loi-ameli/2014-2015/508.html","data":""},{"id":"1465988123536","libelle":"Texte adopté sans modification en 1ère lecture par l'Assemblée nationale le 14 juin 2016","lien":"http://www.assemblee-nationale.fr/14/ta/ta0757.asp","data":""}]},"dossiers":[{"idTexte":"JORFTEXT000032769440","libelleTexte":"LOI n° 2016-832 du 24 juin 2016 visant à lutter contre la discrimination à raison de la précarité sociale (Loi n'appelant pas de décret d'application)","contenuDossier":""}],"refInjection":"IG-20210916","idTechInjection":"JORFDOLE000030746604"}}